{
  "duration": "PT7M48S",
  "view_count": "63827",
  "like_count": "2237",
  "title": "Noam Chomsky: Trump's attacks on China are a continuation of \"Yellow Peril\" fear-mongering",
  "description": "Noam Chomsky says President Trump's move to defund the World Health Organization for its supposed \"insidious relations with China\" is \"typical behavior of autocrats and dictators,\" which is to blame others for your own failures. “In the United States, it’s unfortunately the case … that it’s always easy to blame 'The Yellow Peril.'\" \n\nWatch the full interview with Noam Chomsky: https://youtu.be/d-6EXZ7yM2E\n\n#DemocracyNow\r\n\r\nDemocracy Now! is an independent global news hour that airs on nearly 1,400 TV and radio stations Monday through Friday. Watch our livestream 8-9AM ET: https://democracynow.org\r\n\r\nPlease consider supporting independent media by making a donation to Democracy Now! today: https://democracynow.org/donate\r\n\r\nFOLLOW DEMOCRACY NOW! ONLINE:\r\nYouTube: http://youtube.com/democracynow \r\nFacebook: http://facebook.com/democracynow \r\nTwitter: https://twitter.com/democracynow\r\nInstagram: http://instagram.com/democracynow\r\nSoundCloud: http://soundcloud.com/democracynow \r\niTunes: https://itunes.apple.com/podcast/democracy-now!-audio/id73802554 \r\nDaily Email Digest: https://democracynow.org/subscribe",
  "tags": [
    "Democracy Now",
    "Amy Goodman",
    "News",
    "Politics",
    "democracynow",
    "Independent Media",
    "Breaking News",
    "World News",
    "noam",
    "noam chomsky",
    "noam chomsky 2019",
    "noam chomsky 2020",
    "noam chomsky trump",
    "trump china"
  ],
  "published_at": "2020-04-18T14:00:25Z"
}