{
  "duration": "PT50S",
  "view_count": "529",
  "like_count": "12",
  "title": "The Boldness of Speculation: Chomsky on Creating Social Theories#youtubeshorts #shorts #short #short",
  "description": "Explore Noam Chomsky's insights on the boldness required in creating social theories. In this short video, we delve into Chomsky's views on the importance of speculative thinking in understanding and shaping societies. Discover how his approach to social theory challenges conventional wisdom and inspires innovative perspectives.\n\n#NoamChomsky #SocialTheories #Speculation #Philosophy #InnovativeThinking\n\nDon't forget to like, comment, and subscribe for more thought-provoking insights and intellectual explorations!",
  "tags": [],
  "published_at": "2024-07-02T09:47:17Z"
}