{
  "duration": "PT3M9S",
  "view_count": "27928",
  "like_count": "598",
  "title": "Noam Chomsky - Why Linguistics is at MIT and not at Harvard",
  "description": "",
  "tags": [
    "dissident",
    "intellectual",
    "linguistics",
    "postmodernism",
    "literature",
    "western culture",
    "english",
    "cognitive",
    "revolution",
    "lectures",
    "noam chomsky lectures",
    "american power",
    "new mandarins",
    "humanities",
    "steven pinker",
    "stephen pinker",
    "steve pinker",
    "jordan peterson",
    "marxist",
    "anarchist",
    "howard zinn",
    "artificial intelligence",
    "newton",
    "massachussetts institute of technology",
    "university",
    "free market",
    "alt-right",
    "socialism",
    "communism",
    "soviet union",
    "right"
  ],
  "published_at": "2019-01-04T00:48:43Z"
}