{
  "duration": "PT5M23S",
  "view_count": "396",
  "like_count": "43",
  "title": "18 Quotes That Expose the Dark Side of Modern Society",
  "description": "These quotes will make you stop and think.\n\nSupport my work on Patreon: https://patreon.com/sofoarchon\nFor one-time donations: https://paypal.com/paypalme/theunboundedspirit\n\nIf you found value in this video, be sure to hit like and subscribe.\n\nCONNECT:\nNewsletter: https://sofoarchon.com/newsletter\nInstagram: https://instagram.com/sofoarchon\nFacebook: https://facebook.com/sofoarchon\nX: https://x.com/sofoarchon\n\nTopics explored: quotes, society, culture, modern life, Noam Chomsky, Edward Snowden, Gabor Maté, Karl Marx, Peter Joseph, Martin Luther King Jr., Malcolm X, George Carlin, Arthur Schopenhauer, Charles Bukowski, Bill Hicks, Charles Eisenstein",
  "tags": [],
  "published_at": "2024-10-25T15:01:15Z"
}