{
  "duration": "PT12M21S",
  "view_count": "575601",
  "like_count": "11994",
  "title": "Noam Chomsky - The Most Dangerous Organization in Human History",
  "description": "Source: https://www.youtube.com/watch?v=DFaNajmJ2oc",
  "tags": [
    "GOP",
    "Republican Party",
    "Republicans",
    "Donald Trump",
    "United States",
    "Politics",
    "Climate change",
    "Climate",
    "Trump",
    "Noam Chomsky",
    "Chomsky",
    "U.S.A.",
    "Environment",
    "Pollution",
    "Coal",
    "Paris agreement",
    "Nuclear war",
    "War"
  ],
  "published_at": "2017-05-11T15:06:13Z"
}