{
  "duration": "PT1H2M3S",
  "view_count": "19389",
  "like_count": "473",
  "title": "Noam Chomsky in conversation with Alan Meban",
  "description": "Noam Chomsky in conversation with Alan Meban\nIn this conversation the celebrated American linguist, philosopher, social critic, and political activist discusses the current threats to democracy and ways to build solidarity and progressive politics.\n\nOften described as the father of modern linguistics, Noam Chomsky is also a major figure in analytic philosophy, and one of the founders of the field of cognitive science. He is a Laureate Professor of Linguistics at the University of Arizona and an Institute Professor Emeritus at the Massachusetts Institute of Technology (MIT) and is the author of more than 150 books on topics such as linguistics, war, politics, and mass media.\n\nAlan Meban is a Belfast-based freelance journalist and arts/politics blogger (the face behind @alaninbelfast) who reports from, live-tweets and live-streams civic, academic, and political events; delivers social media training/coaching; produces podcasts and radio programmes; FactCheckNI director; and a member of the Corrymeela Community.\n\nLearn more:  chomsky.info\n\nhttps://imaginebelfast.com/",
  "tags": [
    "Imagine Festival",
    "noam chomsky",
    "alan meban"
  ],
  "published_at": "2023-03-26T15:03:06Z"
}