{
  "duration": "PT3M41S",
  "view_count": "613362",
  "like_count": "8354",
  "title": "Noam Chomsky on The 2024 US Presidential Election.",
  "description": "Watch the full interview with Chomsky Now: https://www.youtube.com/watch?v=av_0PhJdw9M&t=356s\n\nGet the full transcript of the interview here: https://throughconversations.ck.page",
  "tags": [
    "Noam Chomsky",
    "chomsky",
    "trump",
    "2024 elections",
    "presidential elections",
    "2024 presidential elections",
    "democrats",
    "republicans",
    "biden"
  ],
  "published_at": "2023-05-05T23:03:30Z"
}