{
  "duration": "PT1M40S",
  "view_count": "1506",
  "like_count": "60",
  "title": "Noam Chomsky: Is Reality Shaped By Language?",
  "description": "I asked Prof. Chomsky is the reality we perceive and the way we interact with it is shaped by our language or is our language directly influenced by reality. His answer blew my mind.\n\nWatch our full conversation now: https://www.youtube.com/watch?v=zTBsRmn0n3g",
  "tags": [
    "Cognition",
    "Linguistics",
    "MIT",
    "Manufacturing Consent",
    "Noam Chomsky",
    "Socialism",
    "bernie sanders",
    "climate change",
    "donald trump",
    "israel",
    "obama",
    "sam harris",
    "who rules the world"
  ],
  "published_at": "2021-07-07T13:22:37Z"
}